LICENSE
README.md
pyproject.toml
src/esrf_data_compressor/__init__.py
src/esrf_data_compressor/cli.py
src/esrf_data_compressor.egg-info/PKG-INFO
src/esrf_data_compressor.egg-info/SOURCES.txt
src/esrf_data_compressor.egg-info/dependency_links.txt
src/esrf_data_compressor.egg-info/entry_points.txt
src/esrf_data_compressor.egg-info/requires.txt
src/esrf_data_compressor.egg-info/top_level.txt
src/esrf_data_compressor/checker/run_check.py
src/esrf_data_compressor/checker/ssim.py
src/esrf_data_compressor/compressors/__init__.py
src/esrf_data_compressor/compressors/base.py
src/esrf_data_compressor/compressors/jp2k.py
src/esrf_data_compressor/finder/finder.py
src/esrf_data_compressor/tests/__init__.py
src/esrf_data_compressor/tests/test_cli.py
src/esrf_data_compressor/tests/test_finder.py
src/esrf_data_compressor/tests/test_hdf5_helpers.py
src/esrf_data_compressor/tests/test_jp2k.py
src/esrf_data_compressor/tests/test_run_check.py
src/esrf_data_compressor/tests/test_ssim.py
src/esrf_data_compressor/tests/test_utils.py
src/esrf_data_compressor/utils/hdf5_helpers.py
src/esrf_data_compressor/utils/utils.py