Metadata-Version: 2.4
Name: esrf-data-compressor
Version: 0.1.1
Summary: A library to compress ESRF data and reduce their footprint
Author-email: ESRF <dau-pydev@esrf.fr>
License: MIT License
Project-URL: Homepage, https://gitlab.esrf.fr/dau/esrf-data-compressor
Project-URL: Documentation, https://esrf-data-compressor.readthedocs.io/
Project-URL: Repository, https://gitlab.esrf.fr/dau/esrf-data-compressor
Project-URL: Issues, https://gitlab.esrf.fr/dau/esrf-data-compressor/issues
Project-URL: Changelog, https://gitlab.esrf.fr/dau/esrf-data-compressor/-/blob/main/CHANGELOG.md
Keywords: ESRF,pathlib
Classifier: Intended Audience :: Science/Research
Classifier: License :: OSI Approved :: MIT License
Classifier: Programming Language :: Python :: 3
Classifier: Programming Language :: Python :: 3.10
Classifier: Programming Language :: Python :: 3.11
Classifier: Programming Language :: Python :: 3.12
Classifier: Programming Language :: Python :: 3.13
Requires-Python: >=3.10
License-File: LICENSE
Requires-Dist: h5py
Requires-Dist: hdf5plugin
Requires-Dist: blosc2-grok
Requires-Dist: scikit-image
Requires-Dist: tqdm
Provides-Extra: test
Requires-Dist: pytest>=7.0; extra == "test"
Provides-Extra: dev
Requires-Dist: esrf-data-compressor[test]; extra == "dev"
Requires-Dist: black>=22; extra == "dev"
Requires-Dist: flake8>=4.0; extra == "dev"
Requires-Dist: ruff; extra == "dev"
Provides-Extra: doc
Requires-Dist: sphinx>=6.0; extra == "doc"
Requires-Dist: sphinxcontrib-mermaid>=0.7; extra == "doc"
Requires-Dist: sphinx-autodoc-typehints>=1.16; extra == "doc"
Requires-Dist: pydata-sphinx-theme; extra == "doc"
Dynamic: license-file
